{"symbol": "MRK", "summaryProfile": {"sector": "Healthcare", "industry": "Drug Manufacturers\u2014General", "country": "United States"}, "esgScores": {"totalEsg": {"raw": 26.85, "fmt": "26.9"}, "socialScore": {"raw": 14.05, "fmt": "14.1"}, "environmentScore": {"raw": 1.65, "fmt": "1.6"}, "governanceScore": {"raw": 11.15, "fmt": "11.1"}}, "summaryDetail": {"previousClose": {"raw": 80.45, "fmt": "80.45"}, "open": {"raw": 80.61, "fmt": "80.61"}, "bid": {"raw": 80.64, "fmt": "80.64"}, "ask": {"raw": 80.85, "fmt": "80.85"}, "dayLow": {"raw": 79.38, "fmt": "79.38"}, "dayHigh": {"raw": 81.16, "fmt": "81.16"}, "fiftyTwoWeekLow": {"raw": 65.25, "fmt": "65.25"}, "fiftyTwoWeekHigh": {"raw": 92.64, "fmt": "92.64"}, "volume": {"raw": 8474649, "fmt": "8.47M", "longFmt": "8,474,649"}, "averageVolume": {"raw": 8354853, "fmt": "8.35M", "longFmt": "8,354,853"}, "marketCap": {"raw": 203110809600, "fmt": "203.11B", "longFmt": "203,110,809,600"}, "beta": {"raw": 0.427846, "fmt": "0.43"}, "trailingPE": {"raw": 17.729683, "fmt": "17.73"}, "dividendYield": {"raw": 0.0324, "fmt": "3.24%"}, "exDividendDate": {"raw": 1607904000, "fmt": "2020-12-14"}, "forwardPE": {"raw": 12.622641, "fmt": "12.62"}, "priceToSalesTrailing12Months": {"raw": 4.289835, "fmt": "4.29"}, "payoutRatio": {"raw": 0.5386, "fmt": "53.86%"}}, "defaultKeyStatistics": {"trailingEps": {"raw": 4.528, "fmt": "4.53"}, "enterpriseValue": {"raw": 224574160896, "fmt": "224.57B", "longFmt": "224,574,160,896"}, "pegRatio": {"raw": 2.01, "fmt": "2.01"}, "priceToBook": {"raw": 6.9584813, "fmt": "6.96"}, "enterpriseToRevenue": {"raw": 4.743, "fmt": "4.74"}, "enterpriseToEbitda": {"raw": 11.816, "fmt": "11.82"}, "lastFiscalYearEnd": {"raw": 1577750400, "fmt": "2019-12-31"}, "mostRecentQuarter": {"raw": 1601424000, "fmt": "2020-09-30"}, "bookValue": {"raw": 11.537, "fmt": "11.54"}, "52WeekChange": {"raw": -0.080833495, "fmt": "-8.08%"}, "SandP52WeekChange": {"raw": 0.13917124, "fmt": "13.92%"}, "sharesOutstanding": {"raw": 2530030080, "fmt": "2.53B", "longFmt": "2,530,030,080"}, "floatShares": {"raw": 2505189499, "fmt": "2.51B", "longFmt": "2,505,189,499"}, "heldPercentInsiders": {"raw": 0.00077, "fmt": "0.08%"}, "heldPercentInstitutions": {"raw": 0.76125, "fmt": "76.13%"}, "shortRatio": {"raw": 1.72, "fmt": "1.72"}, "sharesShort": {"raw": 14751083, "fmt": "14.75M", "longFmt": "14,751,083"}, "lastSplitFactor": "2:1", "lastSplitDate": {"raw": 919209600, "fmt": "1999-02-17"}}, "earnings": {"earningsChart": {"quarterly": [{"date": "4Q2019", "actual": {"raw": 1.16, "fmt": "1.16"}, "estimate": {"raw": 1.15, "fmt": "1.15"}}, {"date": "1Q2020", "actual": {"raw": 1.5, "fmt": "1.50"}, "estimate": {"raw": 1.34, "fmt": "1.34"}}, {"date": "2Q2020", "actual": {"raw": 1.37, "fmt": "1.37"}, "estimate": {"raw": 1.04, "fmt": "1.04"}}, {"date": "3Q2020", "actual": {"raw": 1.74, "fmt": "1.74"}, "estimate": {"raw": 1.44, "fmt": "1.44"}}], "currentQuarterEstimate": {"raw": 1.38, "fmt": "1.38"}, "currentQuarterEstimateDate": "4Q", "currentQuarterEstimateYear": 2020, "earningsDate": [{"raw": 1612396800, "fmt": "2021-02-04"}]}}, "financialData": {"profitMargins": {"raw": 0.24325001, "fmt": "24.33%"}, "operatingMargins": {"raw": 0.32950002, "fmt": "32.95%"}, "returnOnAssets": {"raw": 0.11264, "fmt": "11.26%"}, "returnOnEquity": {"raw": 0.41057, "fmt": "41.06%"}, "totalRevenue": {"raw": 47346999296, "fmt": "47.35B", "longFmt": "47,346,999,296"}, "revenuePerShare": {"raw": 18.688, "fmt": "18.69"}, "totalDebt": {"raw": 28740999168, "fmt": "28.74B", "longFmt": "28,740,999,168"}, "debtToEquity": {"raw": 98.193, "fmt": "98.19"}, "currentRatio": {"raw": 1.302, "fmt": "1.30"}, "operatingCashflow": {"raw": 11041000448, "fmt": "11.04B", "longFmt": "11,041,000,448"}, "freeCashflow": {"raw": 8651750400, "fmt": "8.65B", "longFmt": "8,651,750,400"}}, "price": {"averageDailyVolume3Month": {"raw": 8354853, "fmt": "8.35M", "longFmt": "8,354,853"}, "averageDailyVolume10Day": {"raw": 8369833, "fmt": "8.37M", "longFmt": "8,369,833"}}, "incomeStatementHistory": {"incomeStatementHistory": [{"researchDevelopment": {"raw": 8742000000, "fmt": "8.74B", "longFmt": "8,742,000,000"}, "effectOfAccountingCharges": {}, "incomeBeforeTax": {"raw": 11464000000, "fmt": "11.46B", "longFmt": "11,464,000,000"}, "minorityInterest": {"raw": 94000000, "fmt": "94M", "longFmt": "94,000,000"}, "netIncome": {"raw": 9843000000, "fmt": "9.84B", "longFmt": "9,843,000,000"}, "sellingGeneralAdministrative": {"raw": 9863000000, "fmt": "9.86B", "longFmt": "9,863,000,000"}, "grossProfit": {"raw": 33684000000, "fmt": "33.68B", "longFmt": "33,684,000,000"}, "ebit": {"raw": 15079000000, "fmt": "15.08B", "longFmt": "15,079,000,000"}, "endDate": {"raw": 1577750400, "fmt": "2019-12-31"}, "operatingIncome": {"raw": 15079000000, "fmt": "15.08B", "longFmt": "15,079,000,000"}, "otherOperatingExpenses": {}, "interestExpense": {"raw": -893000000, "fmt": "-893M", "longFmt": "-893,000,000"}, "extraordinaryItems": {}, "nonRecurring": {}, "otherItems": {}, "incomeTaxExpense": {"raw": 1687000000, "fmt": "1.69B", "longFmt": "1,687,000,000"}, "totalRevenue": {"raw": 46840000000, "fmt": "46.84B", "longFmt": "46,840,000,000"}, "totalOperatingExpenses": {"raw": 31761000000, "fmt": "31.76B", "longFmt": "31,761,000,000"}, "costOfRevenue": {"raw": 13156000000, "fmt": "13.16B", "longFmt": "13,156,000,000"}, "totalOtherIncomeExpenseNet": {"raw": -3615000000, "fmt": "-3.62B", "longFmt": "-3,615,000,000"}, "maxAge": 1, "discontinuedOperations": {}, "netIncomeFromContinuingOps": {"raw": 9777000000, "fmt": "9.78B", "longFmt": "9,777,000,000"}, "netIncomeApplicableToCommonShares": {"raw": 9843000000, "fmt": "9.84B", "longFmt": "9,843,000,000"}}, {"researchDevelopment": {"raw": 9308000000, "fmt": "9.31B", "longFmt": "9,308,000,000"}, "effectOfAccountingCharges": {}, "incomeBeforeTax": {"raw": 8701000000, "fmt": "8.7B", "longFmt": "8,701,000,000"}, "minorityInterest": {"raw": 181000000, "fmt": "181M", "longFmt": "181,000,000"}, "netIncome": {"raw": 6220000000, "fmt": "6.22B", "longFmt": "6,220,000,000"}, "sellingGeneralAdministrative": {"raw": 9555000000, "fmt": "9.55B", "longFmt": "9,555,000,000"}, "grossProfit": {"raw": 28806000000, "fmt": "28.81B", "longFmt": "28,806,000,000"}, "ebit": {"raw": 9943000000, "fmt": "9.94B", "longFmt": "9,943,000,000"}, "endDate": {"raw": 1546214400, "fmt": "2018-12-31"}, "operatingIncome": {"raw": 9943000000, "fmt": "9.94B", "longFmt": "9,943,000,000"}, "otherOperatingExpenses": {}, "interestExpense": {"raw": -772000000, "fmt": "-772M", "longFmt": "-772,000,000"}, "extraordinaryItems": {}, "nonRecurring": {}, "otherItems": {}, "incomeTaxExpense": {"raw": 2508000000, "fmt": "2.51B", "longFmt": "2,508,000,000"}, "totalRevenue": {"raw": 42294000000, "fmt": "42.29B", "longFmt": "42,294,000,000"}, "totalOperatingExpenses": {"raw": 32351000000, "fmt": "32.35B", "longFmt": "32,351,000,000"}, "costOfRevenue": {"raw": 13488000000, "fmt": "13.49B", "longFmt": "13,488,000,000"}, "totalOtherIncomeExpenseNet": {"raw": -1242000000, "fmt": "-1.24B", "longFmt": "-1,242,000,000"}, "maxAge": 1, "discontinuedOperations": {}, "netIncomeFromContinuingOps": {"raw": 6193000000, "fmt": "6.19B", "longFmt": "6,193,000,000"}, "netIncomeApplicableToCommonShares": {"raw": 6220000000, "fmt": "6.22B", "longFmt": "6,220,000,000"}}, {"researchDevelopment": {"raw": 9845000000, "fmt": "9.85B", "longFmt": "9,845,000,000"}, "effectOfAccountingCharges": {}, "incomeBeforeTax": {"raw": 6521000000, "fmt": "6.52B", "longFmt": "6,521,000,000"}, "minorityInterest": {"raw": 233000000, "fmt": "233M", "longFmt": "233,000,000"}, "netIncome": {"raw": 2394000000, "fmt": "2.39B", "longFmt": "2,394,000,000"}, "sellingGeneralAdministrative": {"raw": 9560000000, "fmt": "9.56B", "longFmt": "9,560,000,000"}, "grossProfit": {"raw": 27406000000, "fmt": "27.41B", "longFmt": "27,406,000,000"}, "ebit": {"raw": 8001000000, "fmt": "8B", "longFmt": "8,001,000,000"}, "endDate": {"raw": 1514678400, "fmt": "2017-12-31"}, "operatingIncome": {"raw": 8001000000, "fmt": "8B", "longFmt": "8,001,000,000"}, "otherOperatingExpenses": {}, "interestExpense": {"raw": -754000000, "fmt": "-754M", "longFmt": "-754,000,000"}, "extraordinaryItems": {}, "nonRecurring": {}, "otherItems": {}, "incomeTaxExpense": {"raw": 4103000000, "fmt": "4.1B", "longFmt": "4,103,000,000"}, "totalRevenue": {"raw": 40122000000, "fmt": "40.12B", "longFmt": "40,122,000,000"}, "totalOperatingExpenses": {"raw": 32121000000, "fmt": "32.12B", "longFmt": "32,121,000,000"}, "costOfRevenue": {"raw": 12716000000, "fmt": "12.72B", "longFmt": "12,716,000,000"}, "totalOtherIncomeExpenseNet": {"raw": -1480000000, "fmt": "-1.48B", "longFmt": "-1,480,000,000"}, "maxAge": 1, "discontinuedOperations": {}, "netIncomeFromContinuingOps": {"raw": 2418000000, "fmt": "2.42B", "longFmt": "2,418,000,000"}, "netIncomeApplicableToCommonShares": {"raw": 2394000000, "fmt": "2.39B", "longFmt": "2,394,000,000"}}, {"researchDevelopment": {"raw": 6921000000, "fmt": "6.92B", "longFmt": "6,921,000,000"}, "effectOfAccountingCharges": {}, "incomeBeforeTax": {"raw": 4659000000, "fmt": "4.66B", "longFmt": "4,659,000,000"}, "minorityInterest": {"raw": 220000000, "fmt": "220M", "longFmt": "220,000,000"}, "netIncome": {"raw": 3920000000, "fmt": "3.92B", "longFmt": "3,920,000,000"}, "sellingGeneralAdministrative": {"raw": 9313000000, "fmt": "9.31B", "longFmt": "9,313,000,000"}, "grossProfit": {"raw": 26305000000, "fmt": "26.3B", "longFmt": "26,305,000,000"}, "ebit": {"raw": 10071000000, "fmt": "10.07B", "longFmt": "10,071,000,000"}, "endDate": {"raw": 1483142400, "fmt": "2016-12-31"}, "operatingIncome": {"raw": 10071000000, "fmt": "10.07B", "longFmt": "10,071,000,000"}, "otherOperatingExpenses": {}, "interestExpense": {"raw": -693000000, "fmt": "-693M", "longFmt": "-693,000,000"}, "extraordinaryItems": {}, "nonRecurring": {}, "otherItems": {}, "incomeTaxExpense": {"raw": 718000000, "fmt": "718M", "longFmt": "718,000,000"}, "totalRevenue": {"raw": 39807000000, "fmt": "39.81B", "longFmt": "39,807,000,000"}, "totalOperatingExpenses": {"raw": 29736000000, "fmt": "29.74B", "longFmt": "29,736,000,000"}, "costOfRevenue": {"raw": 13502000000, "fmt": "13.5B", "longFmt": "13,502,000,000"}, "totalOtherIncomeExpenseNet": {"raw": -5412000000, "fmt": "-5.41B", "longFmt": "-5,412,000,000"}, "maxAge": 1, "discontinuedOperations": {}, "netIncomeFromContinuingOps": {"raw": 3941000000, "fmt": "3.94B", "longFmt": "3,941,000,000"}, "netIncomeApplicableToCommonShares": {"raw": 3920000000, "fmt": "3.92B", "longFmt": "3,920,000,000"}}]}, "incomeStatementHistoryQuarterly": {"incomeStatementHistory": [{"researchDevelopment": {"raw": 2539000000, "fmt": "2.54B", "longFmt": "2,539,000,000"}, "effectOfAccountingCharges": {}, "incomeBeforeTax": {"raw": 3428000000, "fmt": "3.43B", "longFmt": "3,428,000,000"}, "minorityInterest": {"raw": 84000000, "fmt": "84M", "longFmt": "84,000,000"}, "netIncome": {"raw": 2941000000, "fmt": "2.94B", "longFmt": "2,941,000,000"}, "sellingGeneralAdministrative": {"raw": 2109000000, "fmt": "2.11B", "longFmt": "2,109,000,000"}, "grossProfit": {"raw": 9108000000, "fmt": "9.11B", "longFmt": "9,108,000,000"}, "ebit": {"raw": 4460000000, "fmt": "4.46B", "longFmt": "4,460,000,000"}, "endDate": {"raw": 1601424000, "fmt": "2020-09-30"}, "operatingIncome": {"raw": 4460000000, "fmt": "4.46B", "longFmt": "4,460,000,000"}, "otherOperatingExpenses": {}, "interestExpense": {"raw": -203000000, "fmt": "-203M", "longFmt": "-203,000,000"}, "extraordinaryItems": {}, "nonRecurring": {}, "otherItems": {}, "incomeTaxExpense": {"raw": 483000000, "fmt": "483M", "longFmt": "483,000,000"}, "totalRevenue": {"raw": 12551000000, "fmt": "12.55B", "longFmt": "12,551,000,000"}, "totalOperatingExpenses": {"raw": 8091000000, "fmt": "8.09B", "longFmt": "8,091,000,000"}, "costOfRevenue": {"raw": 3443000000, "fmt": "3.44B", "longFmt": "3,443,000,000"}, "totalOtherIncomeExpenseNet": {"raw": -1032000000, "fmt": "-1.03B", "longFmt": "-1,032,000,000"}, "maxAge": 1, "discontinuedOperations": {}, "netIncomeFromContinuingOps": {"raw": 2945000000, "fmt": "2.94B", "longFmt": "2,945,000,000"}, "netIncomeApplicableToCommonShares": {"raw": 2941000000, "fmt": "2.94B", "longFmt": "2,941,000,000"}}, {"researchDevelopment": {"raw": 2174000000, "fmt": "2.17B", "longFmt": "2,174,000,000"}, "effectOfAccountingCharges": {}, "incomeBeforeTax": {"raw": 3519000000, "fmt": "3.52B", "longFmt": "3,519,000,000"}, "minorityInterest": {"raw": 102000000, "fmt": "102M", "longFmt": "102,000,000"}, "netIncome": {"raw": 3002000000, "fmt": "3B", "longFmt": "3,002,000,000"}, "sellingGeneralAdministrative": {"raw": 2143000000, "fmt": "2.14B", "longFmt": "2,143,000,000"}, "grossProfit": {"raw": 7738000000, "fmt": "7.74B", "longFmt": "7,738,000,000"}, "ebit": {"raw": 3421000000, "fmt": "3.42B", "longFmt": "3,421,000,000"}, "endDate": {"raw": 1593475200, "fmt": "2020-06-30"}, "operatingIncome": {"raw": 3421000000, "fmt": "3.42B", "longFmt": "3,421,000,000"}, "otherOperatingExpenses": {}, "interestExpense": {"raw": -209000000, "fmt": "-209M", "longFmt": "-209,000,000"}, "extraordinaryItems": {}, "nonRecurring": {}, "otherItems": {}, "incomeTaxExpense": {"raw": 509000000, "fmt": "509M", "longFmt": "509,000,000"}, "totalRevenue": {"raw": 10872000000, "fmt": "10.87B", "longFmt": "10,872,000,000"}, "totalOperatingExpenses": {"raw": 7451000000, "fmt": "7.45B", "longFmt": "7,451,000,000"}, "costOfRevenue": {"raw": 3134000000, "fmt": "3.13B", "longFmt": "3,134,000,000"}, "totalOtherIncomeExpenseNet": {"raw": 98000000, "fmt": "98M", "longFmt": "98,000,000"}, "maxAge": 1, "discontinuedOperations": {}, "netIncomeFromContinuingOps": {"raw": 3010000000, "fmt": "3.01B", "longFmt": "3,010,000,000"}, "netIncomeApplicableToCommonShares": {"raw": 3002000000, "fmt": "3B", "longFmt": "3,002,000,000"}}, {"researchDevelopment": {"raw": 2159000000, "fmt": "2.16B", "longFmt": "2,159,000,000"}, "effectOfAccountingCharges": {}, "incomeBeforeTax": {"raw": 3838000000, "fmt": "3.84B", "longFmt": "3,838,000,000"}, "minorityInterest": {"raw": 95000000, "fmt": "95M", "longFmt": "95,000,000"}, "netIncome": {"raw": 3219000000, "fmt": "3.22B", "longFmt": "3,219,000,000"}, "sellingGeneralAdministrative": {"raw": 2454000000, "fmt": "2.45B", "longFmt": "2,454,000,000"}, "grossProfit": {"raw": 8813000000, "fmt": "8.81B", "longFmt": "8,813,000,000"}, "ebit": {"raw": 4200000000, "fmt": "4.2B", "longFmt": "4,200,000,000"}, "endDate": {"raw": 1585612800, "fmt": "2020-03-31"}, "operatingIncome": {"raw": 4200000000, "fmt": "4.2B", "longFmt": "4,200,000,000"}, "otherOperatingExpenses": {}, "interestExpense": {"raw": -212000000, "fmt": "-212M", "longFmt": "-212,000,000"}, "extraordinaryItems": {}, "nonRecurring": {}, "otherItems": {}, "incomeTaxExpense": {"raw": 619000000, "fmt": "619M", "longFmt": "619,000,000"}, "totalRevenue": {"raw": 12057000000, "fmt": "12.06B", "longFmt": "12,057,000,000"}, "totalOperatingExpenses": {"raw": 7857000000, "fmt": "7.86B", "longFmt": "7,857,000,000"}, "costOfRevenue": {"raw": 3244000000, "fmt": "3.24B", "longFmt": "3,244,000,000"}, "totalOtherIncomeExpenseNet": {"raw": -362000000, "fmt": "-362M", "longFmt": "-362,000,000"}, "maxAge": 1, "discontinuedOperations": {}, "netIncomeFromContinuingOps": {"raw": 3219000000, "fmt": "3.22B", "longFmt": "3,219,000,000"}, "netIncomeApplicableToCommonShares": {"raw": 3219000000, "fmt": "3.22B", "longFmt": "3,219,000,000"}}, {"researchDevelopment": {"raw": 2368000000, "fmt": "2.37B", "longFmt": "2,368,000,000"}, "effectOfAccountingCharges": {}, "incomeBeforeTax": {"raw": 2791000000, "fmt": "2.79B", "longFmt": "2,791,000,000"}, "minorityInterest": {"raw": 94000000, "fmt": "94M", "longFmt": "94,000,000"}, "netIncome": {"raw": 2356000000, "fmt": "2.36B", "longFmt": "2,356,000,000"}, "sellingGeneralAdministrative": {"raw": 2741000000, "fmt": "2.74B", "longFmt": "2,741,000,000"}, "grossProfit": {"raw": 8301000000, "fmt": "8.3B", "longFmt": "8,301,000,000"}, "ebit": {"raw": 3192000000, "fmt": "3.19B", "longFmt": "3,192,000,000"}, "endDate": {"raw": 1577750400, "fmt": "2019-12-31"}, "operatingIncome": {"raw": 3192000000, "fmt": "3.19B", "longFmt": "3,192,000,000"}, "otherOperatingExpenses": {}, "interestExpense": {"raw": -219000000, "fmt": "-219M", "longFmt": "-219,000,000"}, "extraordinaryItems": {}, "nonRecurring": {}, "otherItems": {}, "incomeTaxExpense": {"raw": 428000000, "fmt": "428M", "longFmt": "428,000,000"}, "totalRevenue": {"raw": 11868000000, "fmt": "11.87B", "longFmt": "11,868,000,000"}, "totalOperatingExpenses": {"raw": 8676000000, "fmt": "8.68B", "longFmt": "8,676,000,000"}, "costOfRevenue": {"raw": 3567000000, "fmt": "3.57B", "longFmt": "3,567,000,000"}, "totalOtherIncomeExpenseNet": {"raw": -401000000, "fmt": "-401M", "longFmt": "-401,000,000"}, "maxAge": 1, "discontinuedOperations": {}, "netIncomeFromContinuingOps": {"raw": 2363000000, "fmt": "2.36B", "longFmt": "2,363,000,000"}, "netIncomeApplicableToCommonShares": {"raw": 2356000000, "fmt": "2.36B", "longFmt": "2,356,000,000"}}]}, "balanceSheetHistory": {"balanceSheetStatements": [{"intangibleAssets": {"raw": 14196000000, "fmt": "14.2B", "longFmt": "14,196,000,000"}, "capitalSurplus": {"raw": 39660000000, "fmt": "39.66B", "longFmt": "39,660,000,000"}, "totalLiab": {"raw": 58396000000, "fmt": "58.4B", "longFmt": "58,396,000,000"}, "totalStockholderEquity": {"raw": 25907000000, "fmt": "25.91B", "longFmt": "25,907,000,000"}, "minorityInterest": {"raw": 94000000, "fmt": "94M", "longFmt": "94,000,000"}, "otherCurrentLiab": {"raw": 2452000000, "fmt": "2.45B", "longFmt": "2,452,000,000"}, "totalAssets": {"raw": 84397000000, "fmt": "84.4B", "longFmt": "84,397,000,000"}, "endDate": {"raw": 1577750400, "fmt": "2019-12-31"}, "commonStock": {"raw": 1788000000, "fmt": "1.79B", "longFmt": "1,788,000,000"}, "otherCurrentAssets": {"raw": 3950000000, "fmt": "3.95B", "longFmt": "3,950,000,000"}, "retainedEarnings": {"raw": 46602000000, "fmt": "46.6B", "longFmt": "46,602,000,000"}, "otherLiab": {"raw": 12672000000, "fmt": "12.67B", "longFmt": "12,672,000,000"}, "goodWill": {"raw": 19425000000, "fmt": "19.43B", "longFmt": "19,425,000,000"}, "treasuryStock": {"raw": -62143000000, "fmt": "-62.14B", "longFmt": "-62,143,000,000"}, "otherAssets": {"raw": 5263000000, "fmt": "5.26B", "longFmt": "5,263,000,000"}, "cash": {"raw": 9676000000, "fmt": "9.68B", "longFmt": "9,676,000,000"}, "totalCurrentLiabilities": {"raw": 22220000000, "fmt": "22.22B", "longFmt": "22,220,000,000"}, "deferredLongTermAssetCharges": {"raw": 719000000, "fmt": "719M", "longFmt": "719,000,000"}, "shortLongTermDebt": {"raw": 1901000000, "fmt": "1.9B", "longFmt": "1,901,000,000"}, "otherStockholderEquity": {"raw": -6193000000, "fmt": "-6.19B", "longFmt": "-6,193,000,000"}, "propertyPlantEquipment": {"raw": 16126000000, "fmt": "16.13B", "longFmt": "16,126,000,000"}, "totalCurrentAssets": {"raw": 27483000000, "fmt": "27.48B", "longFmt": "27,483,000,000"}, "longTermInvestments": {"raw": 1904000000, "fmt": "1.9B", "longFmt": "1,904,000,000"}, "netTangibleAssets": {"raw": -7714000000, "fmt": "-7.71B", "longFmt": "-7,714,000,000"}, "shortTermInvestments": {"raw": 774000000, "fmt": "774M", "longFmt": "774,000,000"}, "netReceivables": {"raw": 7105000000, "fmt": "7.11B", "longFmt": "7,105,000,000"}, "maxAge": 1, "longTermDebt": {"raw": 22736000000, "fmt": "22.74B", "longFmt": "22,736,000,000"}, "inventory": {"raw": 5978000000, "fmt": "5.98B", "longFmt": "5,978,000,000"}, "accountsPayable": {"raw": 5015000000, "fmt": "5.01B", "longFmt": "5,015,000,000"}}, {"intangibleAssets": {"raw": 13104000000, "fmt": "13.1B", "longFmt": "13,104,000,000"}, "capitalSurplus": {"raw": 38808000000, "fmt": "38.81B", "longFmt": "38,808,000,000"}, "totalLiab": {"raw": 55755000000, "fmt": "55.76B", "longFmt": "55,755,000,000"}, "totalStockholderEquity": {"raw": 26701000000, "fmt": "26.7B", "longFmt": "26,701,000,000"}, "minorityInterest": {"raw": 181000000, "fmt": "181M", "longFmt": "181,000,000"}, "otherCurrentLiab": {"raw": 3614000000, "fmt": "3.61B", "longFmt": "3,614,000,000"}, "totalAssets": {"raw": 82637000000, "fmt": "82.64B", "longFmt": "82,637,000,000"}, "endDate": {"raw": 1546214400, "fmt": "2018-12-31"}, "commonStock": {"raw": 1788000000, "fmt": "1.79B", "longFmt": "1,788,000,000"}, "otherCurrentAssets": {"raw": 4345000000, "fmt": "4.34B", "longFmt": "4,345,000,000"}, "retainedEarnings": {"raw": 42579000000, "fmt": "42.58B", "longFmt": "42,579,000,000"}, "otherLiab": {"raw": 13662000000, "fmt": "13.66B", "longFmt": "13,662,000,000"}, "goodWill": {"raw": 18253000000, "fmt": "18.25B", "longFmt": "18,253,000,000"}, "treasuryStock": {"raw": -56474000000, "fmt": "-56.47B", "longFmt": "-56,474,000,000"}, "otherAssets": {"raw": 5313000000, "fmt": "5.31B", "longFmt": "5,313,000,000"}, "cash": {"raw": 7965000000, "fmt": "7.96B", "longFmt": "7,965,000,000"}, "totalCurrentLiabilities": {"raw": 22206000000, "fmt": "22.21B", "longFmt": "22,206,000,000"}, "deferredLongTermAssetCharges": {"raw": 656000000, "fmt": "656M", "longFmt": "656,000,000"}, "otherStockholderEquity": {"raw": -5545000000, "fmt": "-5.54B", "longFmt": "-5,545,000,000"}, "propertyPlantEquipment": {"raw": 13291000000, "fmt": "13.29B", "longFmt": "13,291,000,000"}, "totalCurrentAssets": {"raw": 25875000000, "fmt": "25.88B", "longFmt": "25,875,000,000"}, "longTermInvestments": {"raw": 6801000000, "fmt": "6.8B", "longFmt": "6,801,000,000"}, "netTangibleAssets": {"raw": -4656000000, "fmt": "-4.66B", "longFmt": "-4,656,000,000"}, "shortTermInvestments": {"raw": 899000000, "fmt": "899M", "longFmt": "899,000,000"}, "netReceivables": {"raw": 7226000000, "fmt": "7.23B", "longFmt": "7,226,000,000"}, "maxAge": 1, "longTermDebt": {"raw": 19887000000, "fmt": "19.89B", "longFmt": "19,887,000,000"}, "inventory": {"raw": 5440000000, "fmt": "5.44B", "longFmt": "5,440,000,000"}, "accountsPayable": {"raw": 4098000000, "fmt": "4.1B", "longFmt": "4,098,000,000"}}, {"intangibleAssets": {"raw": 14183000000, "fmt": "14.18B", "longFmt": "14,183,000,000"}, "capitalSurplus": {"raw": 39902000000, "fmt": "39.9B", "longFmt": "39,902,000,000"}, "totalLiab": {"raw": 53303000000, "fmt": "53.3B", "longFmt": "53,303,000,000"}, "totalStockholderEquity": {"raw": 34336000000, "fmt": "34.34B", "longFmt": "34,336,000,000"}, "minorityInterest": {"raw": 233000000, "fmt": "233M", "longFmt": "233,000,000"}, "otherCurrentLiab": {"raw": 2192000000, "fmt": "2.19B", "longFmt": "2,192,000,000"}, "totalAssets": {"raw": 87872000000, "fmt": "87.87B", "longFmt": "87,872,000,000"}, "endDate": {"raw": 1514678400, "fmt": "2017-12-31"}, "commonStock": {"raw": 1788000000, "fmt": "1.79B", "longFmt": "1,788,000,000"}, "otherCurrentAssets": {"raw": 4254000000, "fmt": "4.25B", "longFmt": "4,254,000,000"}, "retainedEarnings": {"raw": 41350000000, "fmt": "41.35B", "longFmt": "41,350,000,000"}, "otherLiab": {"raw": 13284000000, "fmt": "13.28B", "longFmt": "13,284,000,000"}, "goodWill": {"raw": 18284000000, "fmt": "18.28B", "longFmt": "18,284,000,000"}, "treasuryStock": {"raw": -48704000000, "fmt": "-48.7B", "longFmt": "-48,704,000,000"}, "otherAssets": {"raw": 6075000000, "fmt": "6.08B", "longFmt": "6,075,000,000"}, "cash": {"raw": 6092000000, "fmt": "6.09B", "longFmt": "6,092,000,000"}, "totalCurrentLiabilities": {"raw": 18614000000, "fmt": "18.61B", "longFmt": "18,614,000,000"}, "deferredLongTermAssetCharges": {"raw": 573000000, "fmt": "573M", "longFmt": "573,000,000"}, "shortLongTermDebt": {"raw": 3003000000, "fmt": "3B", "longFmt": "3,003,000,000"}, "otherStockholderEquity": {"raw": -4910000000, "fmt": "-4.91B", "longFmt": "-4,910,000,000"}, "propertyPlantEquipment": {"raw": 12439000000, "fmt": "12.44B", "longFmt": "12,439,000,000"}, "totalCurrentAssets": {"raw": 24766000000, "fmt": "24.77B", "longFmt": "24,766,000,000"}, "longTermInvestments": {"raw": 12125000000, "fmt": "12.12B", "longFmt": "12,125,000,000"}, "netTangibleAssets": {"raw": 1869000000, "fmt": "1.87B", "longFmt": "1,869,000,000"}, "shortTermInvestments": {"raw": 2406000000, "fmt": "2.41B", "longFmt": "2,406,000,000"}, "netReceivables": {"raw": 6918000000, "fmt": "6.92B", "longFmt": "6,918,000,000"}, "maxAge": 1, "longTermDebt": {"raw": 21405000000, "fmt": "21.41B", "longFmt": "21,405,000,000"}, "inventory": {"raw": 5096000000, "fmt": "5.1B", "longFmt": "5,096,000,000"}, "accountsPayable": {"raw": 3102000000, "fmt": "3.1B", "longFmt": "3,102,000,000"}}, {"intangibleAssets": {"raw": 17305000000, "fmt": "17.3B", "longFmt": "17,305,000,000"}, "capitalSurplus": {"raw": 39939000000, "fmt": "39.94B", "longFmt": "39,939,000,000"}, "totalLiab": {"raw": 55069000000, "fmt": "55.07B", "longFmt": "55,069,000,000"}, "totalStockholderEquity": {"raw": 40088000000, "fmt": "40.09B", "longFmt": "40,088,000,000"}, "minorityInterest": {"raw": 220000000, "fmt": "220M", "longFmt": "220,000,000"}, "otherCurrentLiab": {"raw": 4188000000, "fmt": "4.19B", "longFmt": "4,188,000,000"}, "totalAssets": {"raw": 95377000000, "fmt": "95.38B", "longFmt": "95,377,000,000"}, "endDate": {"raw": 1483142400, "fmt": "2016-12-31"}, "commonStock": {"raw": 1788000000, "fmt": "1.79B", "longFmt": "1,788,000,000"}, "otherCurrentAssets": {"raw": 4389000000, "fmt": "4.39B", "longFmt": "4,389,000,000"}, "retainedEarnings": {"raw": 44133000000, "fmt": "44.13B", "longFmt": "44,133,000,000"}, "otherLiab": {"raw": 13562000000, "fmt": "13.56B", "longFmt": "13,562,000,000"}, "goodWill": {"raw": 18162000000, "fmt": "18.16B", "longFmt": "18,162,000,000"}, "treasuryStock": {"raw": -45772000000, "fmt": "-45.77B", "longFmt": "-45,772,000,000"}, "otherAssets": {"raw": 5834000000, "fmt": "5.83B", "longFmt": "5,834,000,000"}, "cash": {"raw": 6515000000, "fmt": "6.51B", "longFmt": "6,515,000,000"}, "totalCurrentLiabilities": {"raw": 17204000000, "fmt": "17.2B", "longFmt": "17,204,000,000"}, "deferredLongTermAssetCharges": {"raw": 546000000, "fmt": "546M", "longFmt": "546,000,000"}, "shortLongTermDebt": {"raw": 300000000, "fmt": "300M", "longFmt": "300,000,000"}, "otherStockholderEquity": {"raw": -5226000000, "fmt": "-5.23B", "longFmt": "-5,226,000,000"}, "propertyPlantEquipment": {"raw": 12026000000, "fmt": "12.03B", "longFmt": "12,026,000,000"}, "totalCurrentAssets": {"raw": 30614000000, "fmt": "30.61B", "longFmt": "30,614,000,000"}, "longTermInvestments": {"raw": 11436000000, "fmt": "11.44B", "longFmt": "11,436,000,000"}, "netTangibleAssets": {"raw": 4621000000, "fmt": "4.62B", "longFmt": "4,621,000,000"}, "shortTermInvestments": {"raw": 7826000000, "fmt": "7.83B", "longFmt": "7,826,000,000"}, "netReceivables": {"raw": 7018000000, "fmt": "7.02B", "longFmt": "7,018,000,000"}, "maxAge": 1, "longTermDebt": {"raw": 24303000000, "fmt": "24.3B", "longFmt": "24,303,000,000"}, "inventory": {"raw": 4866000000, "fmt": "4.87B", "longFmt": "4,866,000,000"}, "accountsPayable": {"raw": 2807000000, "fmt": "2.81B", "longFmt": "2,807,000,000"}}]}, "balanceSheetHistoryQuarterly": {"balanceSheetStatements": [{"intangibleAssets": {"raw": 16677000000, "fmt": "16.68B", "longFmt": "16,677,000,000"}, "capitalSurplus": {"raw": 39489000000, "fmt": "39.49B", "longFmt": "39,489,000,000"}, "totalLiab": {"raw": 60530000000, "fmt": "60.53B", "longFmt": "60,530,000,000"}, "totalStockholderEquity": {"raw": 29186000000, "fmt": "29.19B", "longFmt": "29,186,000,000"}, "minorityInterest": {"raw": 84000000, "fmt": "84M", "longFmt": "84,000,000"}, "otherCurrentLiab": {"raw": 2848000000, "fmt": "2.85B", "longFmt": "2,848,000,000"}, "totalAssets": {"raw": 89800000000, "fmt": "89.8B", "longFmt": "89,800,000,000"}, "endDate": {"raw": 1601424000, "fmt": "2020-09-30"}, "commonStock": {"raw": 1788000000, "fmt": "1.79B", "longFmt": "1,788,000,000"}, "otherCurrentAssets": {"raw": 4228000000, "fmt": "4.23B", "longFmt": "4,228,000,000"}, "retainedEarnings": {"raw": 51107000000, "fmt": "51.11B", "longFmt": "51,107,000,000"}, "otherLiab": {"raw": 13804000000, "fmt": "13.8B", "longFmt": "13,804,000,000"}, "goodWill": {"raw": 20248000000, "fmt": "20.25B", "longFmt": "20,248,000,000"}, "treasuryStock": {"raw": -63198000000, "fmt": "-63.2B", "longFmt": "-63,198,000,000"}, "otherAssets": {"raw": 7436000000, "fmt": "7.44B", "longFmt": "7,436,000,000"}, "cash": {"raw": 7356000000, "fmt": "7.36B", "longFmt": "7,356,000,000"}, "totalCurrentLiabilities": {"raw": 20405000000, "fmt": "20.41B", "longFmt": "20,405,000,000"}, "otherStockholderEquity": {"raw": -6383000000, "fmt": "-6.38B", "longFmt": "-6,383,000,000"}, "propertyPlantEquipment": {"raw": 16919000000, "fmt": "16.92B", "longFmt": "16,919,000,000"}, "totalCurrentAssets": {"raw": 26577000000, "fmt": "26.58B", "longFmt": "26,577,000,000"}, "longTermInvestments": {"raw": 1943000000, "fmt": "1.94B", "longFmt": "1,943,000,000"}, "netTangibleAssets": {"raw": -7739000000, "fmt": "-7.74B", "longFmt": "-7,739,000,000"}, "netReceivables": {"raw": 8859000000, "fmt": "8.86B", "longFmt": "8,859,000,000"}, "maxAge": 1, "longTermDebt": {"raw": 26321000000, "fmt": "26.32B", "longFmt": "26,321,000,000"}, "inventory": {"raw": 6128000000, "fmt": "6.13B", "longFmt": "6,128,000,000"}, "accountsPayable": {"raw": 4378000000, "fmt": "4.38B", "longFmt": "4,378,000,000"}}, {"intangibleAssets": {"raw": 16566000000, "fmt": "16.57B", "longFmt": "16,566,000,000"}, "capitalSurplus": {"raw": 39373000000, "fmt": "39.37B", "longFmt": "39,373,000,000"}, "totalLiab": {"raw": 62871000000, "fmt": "62.87B", "longFmt": "62,871,000,000"}, "totalStockholderEquity": {"raw": 27642000000, "fmt": "27.64B", "longFmt": "27,642,000,000"}, "minorityInterest": {"raw": 102000000, "fmt": "102M", "longFmt": "102,000,000"}, "otherCurrentLiab": {"raw": 2998000000, "fmt": "3B", "longFmt": "2,998,000,000"}, "totalAssets": {"raw": 90615000000, "fmt": "90.61B", "longFmt": "90,615,000,000"}, "endDate": {"raw": 1593475200, "fmt": "2020-06-30"}, "commonStock": {"raw": 1788000000, "fmt": "1.79B", "longFmt": "1,788,000,000"}, "otherCurrentAssets": {"raw": 4194000000, "fmt": "4.19B", "longFmt": "4,194,000,000"}, "retainedEarnings": {"raw": 49724000000, "fmt": "49.72B", "longFmt": "49,724,000,000"}, "otherLiab": {"raw": 14537000000, "fmt": "14.54B", "longFmt": "14,537,000,000"}, "goodWill": {"raw": 20067000000, "fmt": "20.07B", "longFmt": "20,067,000,000"}, "treasuryStock": {"raw": -63243000000, "fmt": "-63.24B", "longFmt": "-63,243,000,000"}, "otherAssets": {"raw": 7040000000, "fmt": "7.04B", "longFmt": "7,040,000,000"}, "cash": {"raw": 11103000000, "fmt": "11.1B", "longFmt": "11,103,000,000"}, "totalCurrentLiabilities": {"raw": 22178000000, "fmt": "22.18B", "longFmt": "22,178,000,000"}, "otherStockholderEquity": {"raw": -6393000000, "fmt": "-6.39B", "longFmt": "-6,393,000,000"}, "propertyPlantEquipment": {"raw": 15789000000, "fmt": "15.79B", "longFmt": "15,789,000,000"}, "totalCurrentAssets": {"raw": 29343000000, "fmt": "29.34B", "longFmt": "29,343,000,000"}, "longTermInvestments": {"raw": 1810000000, "fmt": "1.81B", "longFmt": "1,810,000,000"}, "netTangibleAssets": {"raw": -8991000000, "fmt": "-8.99B", "longFmt": "-8,991,000,000"}, "netReceivables": {"raw": 7980000000, "fmt": "7.98B", "longFmt": "7,980,000,000"}, "maxAge": 1, "longTermDebt": {"raw": 26156000000, "fmt": "26.16B", "longFmt": "26,156,000,000"}, "inventory": {"raw": 6056000000, "fmt": "6.06B", "longFmt": "6,056,000,000"}, "accountsPayable": {"raw": 4097000000, "fmt": "4.1B", "longFmt": "4,097,000,000"}}, {"intangibleAssets": {"raw": 16096000000, "fmt": "16.1B", "longFmt": "16,096,000,000"}, "capitalSurplus": {"raw": 39697000000, "fmt": "39.7B", "longFmt": "39,697,000,000"}, "totalLiab": {"raw": 58613000000, "fmt": "58.61B", "longFmt": "58,613,000,000"}, "totalStockholderEquity": {"raw": 26205000000, "fmt": "26.2B", "longFmt": "26,205,000,000"}, "minorityInterest": {"raw": 95000000, "fmt": "95M", "longFmt": "95,000,000"}, "otherCurrentLiab": {"raw": 2926000000, "fmt": "2.93B", "longFmt": "2,926,000,000"}, "totalAssets": {"raw": 84913000000, "fmt": "84.91B", "longFmt": "84,913,000,000"}, "endDate": {"raw": 1585612800, "fmt": "2020-03-31"}, "commonStock": {"raw": 1788000000, "fmt": "1.79B", "longFmt": "1,788,000,000"}, "otherCurrentAssets": {"raw": 4371000000, "fmt": "4.37B", "longFmt": "4,371,000,000"}, "retainedEarnings": {"raw": 48272000000, "fmt": "48.27B", "longFmt": "48,272,000,000"}, "otherLiab": {"raw": 13493000000, "fmt": "13.49B", "longFmt": "13,493,000,000"}, "goodWill": {"raw": 19767000000, "fmt": "19.77B", "longFmt": "19,767,000,000"}, "treasuryStock": {"raw": -63552000000, "fmt": "-63.55B", "longFmt": "-63,552,000,000"}, "otherAssets": {"raw": 6532000000, "fmt": "6.53B", "longFmt": "6,532,000,000"}, "cash": {"raw": 7425000000, "fmt": "7.42B", "longFmt": "7,425,000,000"}, "totalCurrentLiabilities": {"raw": 23483000000, "fmt": "23.48B", "longFmt": "23,483,000,000"}, "otherStockholderEquity": {"raw": -6391000000, "fmt": "-6.39B", "longFmt": "-6,391,000,000"}, "propertyPlantEquipment": {"raw": 15269000000, "fmt": "15.27B", "longFmt": "15,269,000,000"}, "totalCurrentAssets": {"raw": 26174000000, "fmt": "26.17B", "longFmt": "26,174,000,000"}, "longTermInvestments": {"raw": 1075000000, "fmt": "1.07B", "longFmt": "1,075,000,000"}, "netTangibleAssets": {"raw": -9658000000, "fmt": "-9.66B", "longFmt": "-9,658,000,000"}, "shortTermInvestments": {"raw": 7000000, "fmt": "7M", "longFmt": "7,000,000"}, "netReceivables": {"raw": 8514000000, "fmt": "8.51B", "longFmt": "8,514,000,000"}, "maxAge": 1, "longTermDebt": {"raw": 21637000000, "fmt": "21.64B", "longFmt": "21,637,000,000"}, "inventory": {"raw": 5846000000, "fmt": "5.85B", "longFmt": "5,846,000,000"}, "accountsPayable": {"raw": 4323000000, "fmt": "4.32B", "longFmt": "4,323,000,000"}}, {"intangibleAssets": {"raw": 14196000000, "fmt": "14.2B", "longFmt": "14,196,000,000"}, "capitalSurplus": {"raw": 39660000000, "fmt": "39.66B", "longFmt": "39,660,000,000"}, "totalLiab": {"raw": 58396000000, "fmt": "58.4B", "longFmt": "58,396,000,000"}, "totalStockholderEquity": {"raw": 25907000000, "fmt": "25.91B", "longFmt": "25,907,000,000"}, "minorityInterest": {"raw": 94000000, "fmt": "94M", "longFmt": "94,000,000"}, "otherCurrentLiab": {"raw": 2452000000, "fmt": "2.45B", "longFmt": "2,452,000,000"}, "totalAssets": {"raw": 84397000000, "fmt": "84.4B", "longFmt": "84,397,000,000"}, "endDate": {"raw": 1577750400, "fmt": "2019-12-31"}, "commonStock": {"raw": 1788000000, "fmt": "1.79B", "longFmt": "1,788,000,000"}, "otherCurrentAssets": {"raw": 3950000000, "fmt": "3.95B", "longFmt": "3,950,000,000"}, "retainedEarnings": {"raw": 46602000000, "fmt": "46.6B", "longFmt": "46,602,000,000"}, "otherLiab": {"raw": 12672000000, "fmt": "12.67B", "longFmt": "12,672,000,000"}, "goodWill": {"raw": 19425000000, "fmt": "19.43B", "longFmt": "19,425,000,000"}, "treasuryStock": {"raw": -62143000000, "fmt": "-62.14B", "longFmt": "-62,143,000,000"}, "otherAssets": {"raw": 5263000000, "fmt": "5.26B", "longFmt": "5,263,000,000"}, "cash": {"raw": 9676000000, "fmt": "9.68B", "longFmt": "9,676,000,000"}, "totalCurrentLiabilities": {"raw": 22220000000, "fmt": "22.22B", "longFmt": "22,220,000,000"}, "deferredLongTermAssetCharges": {"raw": 719000000, "fmt": "719M", "longFmt": "719,000,000"}, "shortLongTermDebt": {"raw": 1901000000, "fmt": "1.9B", "longFmt": "1,901,000,000"}, "otherStockholderEquity": {"raw": -6193000000, "fmt": "-6.19B", "longFmt": "-6,193,000,000"}, "propertyPlantEquipment": {"raw": 16126000000, "fmt": "16.13B", "longFmt": "16,126,000,000"}, "totalCurrentAssets": {"raw": 27483000000, "fmt": "27.48B", "longFmt": "27,483,000,000"}, "longTermInvestments": {"raw": 1904000000, "fmt": "1.9B", "longFmt": "1,904,000,000"}, "netTangibleAssets": {"raw": -7714000000, "fmt": "-7.71B", "longFmt": "-7,714,000,000"}, "shortTermInvestments": {"raw": 774000000, "fmt": "774M", "longFmt": "774,000,000"}, "netReceivables": {"raw": 7105000000, "fmt": "7.11B", "longFmt": "7,105,000,000"}, "maxAge": 1, "longTermDebt": {"raw": 22736000000, "fmt": "22.74B", "longFmt": "22,736,000,000"}, "inventory": {"raw": 5978000000, "fmt": "5.98B", "longFmt": "5,978,000,000"}, "accountsPayable": {"raw": 5015000000, "fmt": "5.01B", "longFmt": "5,015,000,000"}}]}, "cashflowStatementHistory": {"cashflowStatements": [{"investments": {"raw": 5420000000, "fmt": "5.42B", "longFmt": "5,420,000,000"}, "changeToLiabilities": {"raw": 399000000, "fmt": "399M", "longFmt": "399,000,000"}, "totalCashflowsFromInvestingActivities": {"raw": -2629000000, "fmt": "-2.63B", "longFmt": "-2,629,000,000"}, "netBorrowings": {"raw": 1248000000, "fmt": "1.25B", "longFmt": "1,248,000,000"}, "totalCashFromFinancingActivities": {"raw": -8861000000, "fmt": "-8.86B", "longFmt": "-8,861,000,000"}, "changeToOperatingActivities": {"raw": 107000000, "fmt": "107M", "longFmt": "107,000,000"}, "issuanceOfStock": {"raw": 361000000, "fmt": "361M", "longFmt": "361,000,000"}, "netIncome": {"raw": 9843000000, "fmt": "9.84B", "longFmt": "9,843,000,000"}, "changeInCash": {"raw": 1967000000, "fmt": "1.97B", "longFmt": "1,967,000,000"}, "endDate": {"raw": 1577750400, "fmt": "2019-12-31"}, "repurchaseOfStock": {"raw": -4780000000, "fmt": "-4.78B", "longFmt": "-4,780,000,000"}, "effectOfExchangeRate": {"raw": 17000000, "fmt": "17M", "longFmt": "17,000,000"}, "totalCashFromOperatingActivities": {"raw": 13440000000, "fmt": "13.44B", "longFmt": "13,440,000,000"}, "depreciation": {"raw": 3419000000, "fmt": "3.42B", "longFmt": "3,419,000,000"}, "otherCashflowsFromInvestingActivities": {"raw": 378000000, "fmt": "378M", "longFmt": "378,000,000"}, "dividendsPaid": {"raw": -5695000000, "fmt": "-5.7B", "longFmt": "-5,695,000,000"}, "changeToInventory": {"raw": -508000000, "fmt": "-508M", "longFmt": "-508,000,000"}, "changeToAccountReceivables": {"raw": 294000000, "fmt": "294M", "longFmt": "294,000,000"}, "otherCashflowsFromFinancingActivities": {"raw": 5000000, "fmt": "5M", "longFmt": "5,000,000"}, "maxAge": 1, "changeToNetincome": {"raw": 2245000000, "fmt": "2.25B", "longFmt": "2,245,000,000"}, "capitalExpenditures": {"raw": -3473000000, "fmt": "-3.47B", "longFmt": "-3,473,000,000"}}, {"investments": {"raw": 7258000000, "fmt": "7.26B", "longFmt": "7,258,000,000"}, "changeToLiabilities": {"raw": 230000000, "fmt": "230M", "longFmt": "230,000,000"}, "totalCashflowsFromInvestingActivities": {"raw": 4314000000, "fmt": "4.31B", "longFmt": "4,314,000,000"}, "netBorrowings": {"raw": 837000000, "fmt": "837M", "longFmt": "837,000,000"}, "totalCashFromFinancingActivities": {"raw": -13160000000, "fmt": "-13.16B", "longFmt": "-13,160,000,000"}, "changeToOperatingActivities": {"raw": -1281000000, "fmt": "-1.28B", "longFmt": "-1,281,000,000"}, "issuanceOfStock": {"raw": 591000000, "fmt": "591M", "longFmt": "591,000,000"}, "netIncome": {"raw": 6220000000, "fmt": "6.22B", "longFmt": "6,220,000,000"}, "changeInCash": {"raw": 1871000000, "fmt": "1.87B", "longFmt": "1,871,000,000"}, "endDate": {"raw": 1546214400, "fmt": "2018-12-31"}, "repurchaseOfStock": {"raw": -9091000000, "fmt": "-9.09B", "longFmt": "-9,091,000,000"}, "effectOfExchangeRate": {"raw": -205000000, "fmt": "-205M", "longFmt": "-205,000,000"}, "totalCashFromOperatingActivities": {"raw": 10922000000, "fmt": "10.92B", "longFmt": "10,922,000,000"}, "depreciation": {"raw": 4520000000, "fmt": "4.52B", "longFmt": "4,520,000,000"}, "otherCashflowsFromInvestingActivities": {"raw": 102000000, "fmt": "102M", "longFmt": "102,000,000"}, "dividendsPaid": {"raw": -5172000000, "fmt": "-5.17B", "longFmt": "-5,172,000,000"}, "changeToInventory": {"raw": -911000000, "fmt": "-911M", "longFmt": "-911,000,000"}, "changeToAccountReceivables": {"raw": -418000000, "fmt": "-418M", "longFmt": "-418,000,000"}, "otherCashflowsFromFinancingActivities": {"raw": -325000000, "fmt": "-325M", "longFmt": "-325,000,000"}, "maxAge": 1, "changeToNetincome": {"raw": 1735000000, "fmt": "1.74B", "longFmt": "1,735,000,000"}, "capitalExpenditures": {"raw": -2615000000, "fmt": "-2.62B", "longFmt": "-2,615,000,000"}}, {"investments": {"raw": 4925000000, "fmt": "4.92B", "longFmt": "4,925,000,000"}, "changeToLiabilities": {"raw": 254000000, "fmt": "254M", "longFmt": "254,000,000"}, "totalCashflowsFromInvestingActivities": {"raw": 2679000000, "fmt": "2.68B", "longFmt": "2,679,000,000"}, "netBorrowings": {"raw": -1129000000, "fmt": "-1.13B", "longFmt": "-1,129,000,000"}, "totalCashFromFinancingActivities": {"raw": -10006000000, "fmt": "-10.01B", "longFmt": "-10,006,000,000"}, "changeToOperatingActivities": {"raw": -2132000000, "fmt": "-2.13B", "longFmt": "-2,132,000,000"}, "issuanceOfStock": {"raw": 499000000, "fmt": "499M", "longFmt": "499,000,000"}, "netIncome": {"raw": 2394000000, "fmt": "2.39B", "longFmt": "2,394,000,000"}, "changeInCash": {"raw": -419000000, "fmt": "-419M", "longFmt": "-419,000,000"}, "endDate": {"raw": 1514678400, "fmt": "2017-12-31"}, "repurchaseOfStock": {"raw": -4014000000, "fmt": "-4.01B", "longFmt": "-4,014,000,000"}, "effectOfExchangeRate": {"raw": 457000000, "fmt": "457M", "longFmt": "457,000,000"}, "totalCashFromOperatingActivities": {"raw": 6451000000, "fmt": "6.45B", "longFmt": "6,451,000,000"}, "depreciation": {"raw": 4616000000, "fmt": "4.62B", "longFmt": "4,616,000,000"}, "otherCashflowsFromInvestingActivities": {"raw": 38000000, "fmt": "38M", "longFmt": "38,000,000"}, "dividendsPaid": {"raw": -5167000000, "fmt": "-5.17B", "longFmt": "-5,167,000,000"}, "changeToInventory": {"raw": -145000000, "fmt": "-145M", "longFmt": "-145,000,000"}, "changeToAccountReceivables": {"raw": 297000000, "fmt": "297M", "longFmt": "297,000,000"}, "otherCashflowsFromFinancingActivities": {"raw": -195000000, "fmt": "-195M", "longFmt": "-195,000,000"}, "maxAge": 1, "changeToNetincome": {"raw": 4458000000, "fmt": "4.46B", "longFmt": "4,458,000,000"}, "capitalExpenditures": {"raw": -1888000000, "fmt": "-1.89B", "longFmt": "-1,888,000,000"}}, {"investments": {"raw": -1298000000, "fmt": "-1.3B", "longFmt": "-1,298,000,000"}, "changeToLiabilities": {"raw": 278000000, "fmt": "278M", "longFmt": "278,000,000"}, "totalCashflowsFromInvestingActivities": {"raw": -3210000000, "fmt": "-3.21B", "longFmt": "-3,210,000,000"}, "netBorrowings": {"raw": -1307000000, "fmt": "-1.31B", "longFmt": "-1,307,000,000"}, "totalCashFromFinancingActivities": {"raw": -9044000000, "fmt": "-9.04B", "longFmt": "-9,044,000,000"}, "changeToOperatingActivities": {"raw": -2590000000, "fmt": "-2.59B", "longFmt": "-2,590,000,000"}, "issuanceOfStock": {"raw": 939000000, "fmt": "939M", "longFmt": "939,000,000"}, "netIncome": {"raw": 3920000000, "fmt": "3.92B", "longFmt": "3,920,000,000"}, "changeInCash": {"raw": -2009000000, "fmt": "-2.01B", "longFmt": "-2,009,000,000"}, "endDate": {"raw": 1483142400, "fmt": "2016-12-31"}, "repurchaseOfStock": {"raw": -3434000000, "fmt": "-3.43B", "longFmt": "-3,434,000,000"}, "effectOfExchangeRate": {"raw": -131000000, "fmt": "-131M", "longFmt": "-131,000,000"}, "totalCashFromOperatingActivities": {"raw": 10376000000, "fmt": "10.38B", "longFmt": "10,376,000,000"}, "depreciation": {"raw": 5244000000, "fmt": "5.24B", "longFmt": "5,244,000,000"}, "otherCashflowsFromInvestingActivities": {"raw": 482000000, "fmt": "482M", "longFmt": "482,000,000"}, "dividendsPaid": {"raw": -5124000000, "fmt": "-5.12B", "longFmt": "-5,124,000,000"}, "changeToInventory": {"raw": 206000000, "fmt": "206M", "longFmt": "206,000,000"}, "changeToAccountReceivables": {"raw": -619000000, "fmt": "-619M", "longFmt": "-619,000,000"}, "otherCashflowsFromFinancingActivities": {"raw": -118000000, "fmt": "-118M", "longFmt": "-118,000,000"}, "maxAge": 1, "changeToNetincome": {"raw": 3813000000, "fmt": "3.81B", "longFmt": "3,813,000,000"}, "capitalExpenditures": {"raw": -1614000000, "fmt": "-1.61B", "longFmt": "-1,614,000,000"}}]}, "cashflowStatementHistoryQuarterly": {"cashflowStatements": [{"investments": {"raw": 1000000, "fmt": "1M", "longFmt": "1,000,000"}, "changeToLiabilities": {"raw": 0, "fmt": null, "longFmt": "0"}, "totalCashflowsFromInvestingActivities": {"raw": -2155000000, "fmt": "-2.15B", "longFmt": "-2,155,000,000"}, "netBorrowings": {"raw": -2306000000, "fmt": "-2.31B", "longFmt": "-2,306,000,000"}, "totalCashFromFinancingActivities": {"raw": -3851000000, "fmt": "-3.85B", "longFmt": "-3,851,000,000"}, "changeToOperatingActivities": {"raw": -1445000000, "fmt": "-1.45B", "longFmt": "-1,445,000,000"}, "issuanceOfStock": {"raw": 28000000, "fmt": "28M", "longFmt": "28,000,000"}, "netIncome": {"raw": 2941000000, "fmt": "2.94B", "longFmt": "2,941,000,000"}, "changeInCash": {"raw": -3746000000, "fmt": "-3.75B", "longFmt": "-3,746,000,000"}, "endDate": {"raw": 1601424000, "fmt": "2020-09-30"}, "effectOfExchangeRate": {"raw": 87000000, "fmt": "87M", "longFmt": "87,000,000"}, "totalCashFromOperatingActivities": {"raw": 2173000000, "fmt": "2.17B", "longFmt": "2,173,000,000"}, "depreciation": {"raw": 786000000, "fmt": "786M", "longFmt": "786,000,000"}, "otherCashflowsFromInvestingActivities": {"raw": -54000000, "fmt": "-54M", "longFmt": "-54,000,000"}, "dividendsPaid": {"raw": -1545000000, "fmt": "-1.54B", "longFmt": "-1,545,000,000"}, "otherCashflowsFromFinancingActivities": {"raw": -28000000, "fmt": "-28M", "longFmt": "-28,000,000"}, "maxAge": 1, "changeToNetincome": {"raw": -108000000, "fmt": "-108M", "longFmt": "-108,000,000"}, "capitalExpenditures": {"raw": -1516000000, "fmt": "-1.52B", "longFmt": "-1,516,000,000"}}, {"investments": {"raw": 48000000, "fmt": "48M", "longFmt": "48,000,000"}, "changeToLiabilities": {"raw": 0, "fmt": null, "longFmt": "0"}, "totalCashflowsFromInvestingActivities": {"raw": -882000000, "fmt": "-882M", "longFmt": "-882,000,000"}, "netBorrowings": {"raw": 2828000000, "fmt": "2.83B", "longFmt": "2,828,000,000"}, "totalCashFromFinancingActivities": {"raw": 1137000000, "fmt": "1.14B", "longFmt": "1,137,000,000"}, "changeToOperatingActivities": {"raw": -527000000, "fmt": "-527M", "longFmt": "-527,000,000"}, "issuanceOfStock": {"raw": 14000000, "fmt": "14M", "longFmt": "14,000,000"}, "netIncome": {"raw": 3002000000, "fmt": "3B", "longFmt": "3,002,000,000"}, "changeInCash": {"raw": 3687000000, "fmt": "3.69B", "longFmt": "3,687,000,000"}, "endDate": {"raw": 1593475200, "fmt": "2020-06-30"}, "effectOfExchangeRate": {"raw": 65000000, "fmt": "65M", "longFmt": "65,000,000"}, "totalCashFromOperatingActivities": {"raw": 3367000000, "fmt": "3.37B", "longFmt": "3,367,000,000"}, "depreciation": {"raw": 975000000, "fmt": "975M", "longFmt": "975,000,000"}, "otherCashflowsFromInvestingActivities": {"raw": 59000000, "fmt": "59M", "longFmt": "59,000,000"}, "dividendsPaid": {"raw": -1577000000, "fmt": "-1.58B", "longFmt": "-1,577,000,000"}, "otherCashflowsFromFinancingActivities": {"raw": -128000000, "fmt": "-128M", "longFmt": "-128,000,000"}, "maxAge": 1, "changeToNetincome": {"raw": -83000000, "fmt": "-83M", "longFmt": "-83,000,000"}, "capitalExpenditures": {"raw": -668000000, "fmt": "-668M", "longFmt": "-668,000,000"}}, {"investments": {"raw": 1767000000, "fmt": "1.77B", "longFmt": "1,767,000,000"}, "changeToLiabilities": {"raw": 0, "fmt": null, "longFmt": "0"}, "totalCashflowsFromInvestingActivities": {"raw": -1628000000, "fmt": "-1.63B", "longFmt": "-1,628,000,000"}, "netBorrowings": {"raw": 1632000000, "fmt": "1.63B", "longFmt": "1,632,000,000"}, "totalCashFromFinancingActivities": {"raw": -1490000000, "fmt": "-1.49B", "longFmt": "-1,490,000,000"}, "changeToOperatingActivities": {"raw": -3666000000, "fmt": "-3.67B", "longFmt": "-3,666,000,000"}, "issuanceOfStock": {"raw": 26000000, "fmt": "26M", "longFmt": "26,000,000"}, "netIncome": {"raw": 3219000000, "fmt": "3.22B", "longFmt": "3,219,000,000"}, "changeInCash": {"raw": -2474000000, "fmt": "-2.47B", "longFmt": "-2,474,000,000"}, "endDate": {"raw": 1585612800, "fmt": "2020-03-31"}, "repurchaseOfStock": {"raw": -1281000000, "fmt": "-1.28B", "longFmt": "-1,281,000,000"}, "effectOfExchangeRate": {"raw": -63000000, "fmt": "-63M", "longFmt": "-63,000,000"}, "totalCashFromOperatingActivities": {"raw": 707000000, "fmt": "707M", "longFmt": "707,000,000"}, "depreciation": {"raw": 768000000, "fmt": "768M", "longFmt": "768,000,000"}, "otherCashflowsFromInvestingActivities": {"raw": 136000000, "fmt": "136M", "longFmt": "136,000,000"}, "dividendsPaid": {"raw": -1551000000, "fmt": "-1.55B", "longFmt": "-1,551,000,000"}, "otherCashflowsFromFinancingActivities": {"raw": -316000000, "fmt": "-316M", "longFmt": "-316,000,000"}, "maxAge": 1, "changeToNetincome": {"raw": 386000000, "fmt": "386M", "longFmt": "386,000,000"}, "capitalExpenditures": {"raw": -986000000, "fmt": "-986M", "longFmt": "-986,000,000"}}, {"investments": {"raw": 341000000, "fmt": "341M", "longFmt": "341,000,000"}, "changeToLiabilities": {"raw": 399000000, "fmt": "399M", "longFmt": "399,000,000"}, "totalCashflowsFromInvestingActivities": {"raw": -763000000, "fmt": "-763M", "longFmt": "-763,000,000"}, "netBorrowings": {"raw": 182000000, "fmt": "182M", "longFmt": "182,000,000"}, "totalCashFromFinancingActivities": {"raw": -2011000000, "fmt": "-2.01B", "longFmt": "-2,011,000,000"}, "changeToOperatingActivities": {"raw": 3576000000, "fmt": "3.58B", "longFmt": "3,576,000,000"}, "issuanceOfStock": {"raw": 17000000, "fmt": "17M", "longFmt": "17,000,000"}, "netIncome": {"raw": 2356000000, "fmt": "2.36B", "longFmt": "2,356,000,000"}, "changeInCash": {"raw": 2063000000, "fmt": "2.06B", "longFmt": "2,063,000,000"}, "endDate": {"raw": 1577750400, "fmt": "2019-12-31"}, "repurchaseOfStock": {"raw": -1050000000, "fmt": "-1.05B", "longFmt": "-1,050,000,000"}, "effectOfExchangeRate": {"raw": 43000000, "fmt": "43M", "longFmt": "43,000,000"}, "totalCashFromOperatingActivities": {"raw": 4794000000, "fmt": "4.79B", "longFmt": "4,794,000,000"}, "depreciation": {"raw": 876000000, "fmt": "876M", "longFmt": "876,000,000"}, "otherCashflowsFromInvestingActivities": {"raw": 58000000, "fmt": "58M", "longFmt": "58,000,000"}, "dividendsPaid": {"raw": -1405000000, "fmt": "-1.41B", "longFmt": "-1,405,000,000"}, "changeToInventory": {"raw": -508000000, "fmt": "-508M", "longFmt": "-508,000,000"}, "changeToAccountReceivables": {"raw": 294000000, "fmt": "294M", "longFmt": "294,000,000"}, "otherCashflowsFromFinancingActivities": {"raw": 245000000, "fmt": "245M", "longFmt": "245,000,000"}, "maxAge": 1, "changeToNetincome": {"raw": 160000000, "fmt": "160M", "longFmt": "160,000,000"}, "capitalExpenditures": {"raw": -1137000000, "fmt": "-1.14B", "longFmt": "-1,137,000,000"}}]}, "timeSeries": {"annualBasicEPS": [{"dataId": 29004, "asOfDate": "2016-12-31", "periodType": "12M", "currencyCode": "USD", "reportedValue": {"raw": 2.07041, "fmt": "2.07"}}, {"dataId": 29004, "asOfDate": "2017-12-31", "periodType": "12M", "currencyCode": "USD", "reportedValue": {"raw": 0.952306, "fmt": "0.95"}}, {"dataId": 29004, "asOfDate": "2018-12-31", "periodType": "12M", "currencyCode": "USD", "reportedValue": {"raw": 2.399173, "fmt": "2.40"}}, {"dataId": 29004, "asOfDate": "2019-12-31", "periodType": "12M", "currencyCode": "USD", "reportedValue": {"raw": 3.876699, "fmt": "3.88"}}], "annualDilutedEPS": [{"dataId": 29009, "asOfDate": "2016-12-31", "periodType": "12M", "currencyCode": "USD", "reportedValue": {"raw": 2.04, "fmt": "2.04"}}, {"dataId": 29009, "asOfDate": "2017-12-31", "periodType": "12M", "currencyCode": "USD", "reportedValue": {"raw": 0.93, "fmt": "0.93"}}, {"dataId": 29009, "asOfDate": "2018-12-31", "periodType": "12M", "currencyCode": "USD", "reportedValue": {"raw": 2.32, "fmt": "2.32"}}, {"dataId": 29009, "asOfDate": "2019-12-31", "periodType": "12M", "currencyCode": "USD", "reportedValue": {"raw": 3.81, "fmt": "3.81"}}], "annualBasicAverageShares": [{"dataId": 29010, "asOfDate": "2016-12-31", "periodType": "12M", "currencyCode": "USD", "reportedValue": {"raw": 2748731322, "fmt": "2.75B"}}, {"dataId": 29010, "asOfDate": "2017-12-31", "periodType": "12M", "currencyCode": "USD", "reportedValue": {"raw": 2696611608, "fmt": "2.70B"}}, {"dataId": 29010, "asOfDate": "2018-12-31", "periodType": "12M", "currencyCode": "USD", "reportedValue": {"raw": 2592559543, "fmt": "2.59B"}}, {"dataId": 29010, "asOfDate": "2019-12-31", "periodType": "12M", "currencyCode": "USD", "reportedValue": {"raw": 2539016026, "fmt": "2.54B"}}], "annualDilutedAverageShares": [{"dataId": 29011, "asOfDate": "2016-12-31", "periodType": "12M", "currencyCode": "USD", "reportedValue": {"raw": 2787000000, "fmt": "2.79B"}}, {"dataId": 29011, "asOfDate": "2017-12-31", "periodType": "12M", "currencyCode": "USD", "reportedValue": {"raw": 2748000000, "fmt": "2.75B"}}, {"dataId": 29011, "asOfDate": "2018-12-31", "periodType": "12M", "currencyCode": "USD", "reportedValue": {"raw": 2679000000, "fmt": "2.68B"}}, {"dataId": 29011, "asOfDate": "2019-12-31", "periodType": "12M", "currencyCode": "USD", "reportedValue": {"raw": 2580000000, "fmt": "2.58B"}}], "annualEbitda": [{"dataId": 20190, "asOfDate": "2016-12-31", "periodType": "12M", "currencyCode": "USD", "reportedValue": {"raw": 10793000000, "fmt": "10.79B"}}, {"dataId": 20190, "asOfDate": "2017-12-31", "periodType": "12M", "currencyCode": "USD", "reportedValue": {"raw": 11912000000, "fmt": "11.91B"}}, {"dataId": 20190, "asOfDate": "2018-12-31", "periodType": "12M", "currencyCode": "USD", "reportedValue": {"raw": 13992000000, "fmt": "13.99B"}}, {"dataId": 20190, "asOfDate": "2019-12-31", "periodType": "12M", "currencyCode": "USD", "reportedValue": {"raw": 16009000000, "fmt": "16.01B"}}]}, "investing": {"dividend": 2.6, "stock_price": 80.06}}